Metadata-Version: 2.1
Name: becloud
Version: 0.1.2
Summary: Backend Cloud Package
Home-page: UNKNOWN
License: UNKNOWN
Platform: UNKNOWN
